mcp_registry/__init__.py
mcp_registry/cli.py
mcp_registry/compound.py
mcp_registry/connection.py
mcp_registry/commands/__init__.py
mcp_registry/commands/serve.py
mcp_registry/commands/tools.py
mcp_registry/utils/__init__.py
mcp_registry/utils/cli.py
mcp_registry/utils/config.py
mcp_registry/utils/formatters.py
mcp_registry/utils/parameter_collectors.py
mcp_registry/utils/tool_helpers.py
mcp_registry-0.9.2.dist-info/METADATA
mcp_registry-0.9.2.dist-info/WHEEL
mcp_registry-0.9.2.dist-info/entry_points.txt
mcp_registry-0.9.2.dist-info/licenses/LICENSE
mcp_registry-0.9.2.dist-info/RECORD
